libmiaa/__init__.py
libmiaa/modulo.py
libmiaa-0.2.4.dist-info/METADATA
libmiaa-0.2.4.dist-info/WHEEL
libmiaa-0.2.4.dist-info/top_level.txt
libmiaa-0.2.4.dist-info/RECORD
