Metadata-Version: 2.1
Name: libmiaa
Version: 0.2.4
Summary: libreria de suma
Author: Emmanuel Botero  
Author-email: emmanuel.botero@udea.edu.co
License: MIT
Requires-Python: >=3.10.12
Requires-Dist: numpy ==1.26.1
Requires-Dist: pandas ==2.1.1
